stata_mcp/__init__.py
stata_mcp/config.py
stata_mcp/mcp_servers.py
stata_mcp/agent_as/__init__.py
stata_mcp/agent_as/agent_base.py
stata_mcp/agent_as/repl_agents.py
stata_mcp/agent_as/set_model.py
stata_mcp/agent_as/agent_as_rag/__init__.py
stata_mcp/agent_as/agent_as_rag/_tools.py
stata_mcp/agent_as/agent_as_rag/base.py
stata_mcp/agent_as/agent_as_rag/handoff.py
stata_mcp/agent_as/agent_as_tool/__init__.py
stata_mcp/agent_as/agent_as_tool/adversarial_thinking_agent.py
stata_mcp/agent_as/agent_as_tool/any_as_tools.py
stata_mcp/agent_as/agent_as_tool/stata_agent.py
stata_mcp/cli/__init__.py
stata_mcp/cli/_cli.py
stata_mcp/core/__init__.py
stata_mcp/core/claude_proj/__init__.py
stata_mcp/core/claude_proj/claude_cfg.py
stata_mcp/core/claude_proj/cwd_cfg.py
stata_mcp/core/claude_proj/proj.py
stata_mcp/core/data_info/__init__.py
stata_mcp/core/data_info/base.py
stata_mcp/core/data_info/csv.py
stata_mcp/core/data_info/dta.py
stata_mcp/core/data_info/xlsx.py
stata_mcp/core/stata/__init__.py
stata_mcp/core/stata/builtin_tools/__init__.py
stata_mcp/core/stata/builtin_tools/ado_install/__init__.py
stata_mcp/core/stata/builtin_tools/ado_install/base.py
stata_mcp/core/stata/builtin_tools/ado_install/github_install.py
stata_mcp/core/stata/builtin_tools/ado_install/net_install.py
stata_mcp/core/stata/builtin_tools/ado_install/ssc_install.py
stata_mcp/core/stata/builtin_tools/help/__init__.py
stata_mcp/core/stata/builtin_tools/help/stata_help.py
stata_mcp/core/stata/stata_controller/__init__.py
stata_mcp/core/stata/stata_controller/controller.py
stata_mcp/core/stata/stata_do/__init__.py
stata_mcp/core/stata/stata_do/do.py
stata_mcp/core/stata/stata_finder/__init__.py
stata_mcp/core/stata/stata_finder/base.py
stata_mcp/core/stata/stata_finder/finder.py
stata_mcp/core/stata/stata_finder/linux.py
stata_mcp/core/stata/stata_finder/macos.py
stata_mcp/core/stata/stata_finder/windows.py
stata_mcp/core/types/__init__.py
stata_mcp/core/types/_error.py
stata_mcp/evaluate/__init__.py
stata_mcp-1.13.29.dist-info/METADATA
stata_mcp-1.13.29.dist-info/WHEEL
stata_mcp-1.13.29.dist-info/entry_points.txt
stata_mcp-1.13.29.dist-info/licenses/LICENSE
stata_mcp-1.13.29.dist-info/RECORD
