Metadata-Version: 2.4
Name: stata-mcp
Version: 1.13.29
Summary: Let LLM help you achieve your regression analysis with Stata
Project-URL: Homepage, https://www.statamcp.com
Project-URL: Documentation, https://docs.statamcp.com
Project-URL: Source, https://github.com/sepinetam/stata-mcp
Project-URL: Issues, https://github.com/sepinetam/stata-mcp/issues
Project-URL: Changelog, https://github.com/sepinetam/stata-mcp/blob/master/CHANGELOG.md
Author-email: Song Tan <sepinetam@gmail.com>
License: AGPL-3.0
License-File: LICENSE
Keywords: agent,ai,econometrics,mcp,stata
Requires-Python: >=3.11
Requires-Dist: mcp-ui-server>=1.0.0
Requires-Dist: mcp[cli]>=1.23.0
Requires-Dist: openai-agents>=0.3.2
Requires-Dist: openai-api-polling>=0.1.2
Requires-Dist: openai>=1.109.1
Requires-Dist: openpyxl>=3.1.5
Requires-Dist: pandas<3.0.0,>=2.3.0
Requires-Dist: pathvalidate>=3.3.1
Requires-Dist: pexpect>=4.9.0
Requires-Dist: psutil>=6.0.0
Requires-Dist: python-dotenv>=1.2.1
